[
    {
        "report_md": "html_stock/1034_코스피100/1d/RANK_2_[LH39.0_HL-2.17]_삼성전자/report.md",
        "report_csv": "html_stock/1034_코스피100/1d/RANK_2_[LH39.0_HL-2.17]_삼성전자/report.csv",
        "bodycontents_html": "html_stock/1034_코스피100/1d/RANK_2_[LH39.0_HL-2.17]_삼성전자/bodycontents.html",
        "view_md": "html_stock/1034_코스피100/1d/RANK_2_[LH39.0_HL-2.17]_삼성전자/view.md",
        "ptlotlychart_md": "html_stock/1034_코스피100/1d/RANK_2_[LH39.0_HL-2.17]_삼성전자/ptlotlychart.md",
        "ptlotlychart_png": "html_stock/1034_코스피100/1d/RANK_2_[LH39.0_HL-2.17]_삼성전자/ptlotlychart.png",
        "thumbnail_png": "html_stock/1034_코스피100/1d/RANK_2_[LH39.0_HL-2.17]_삼성전자/thumbnail_png.png",
        "contents_png": "html_stock/1034_코스피100/1d/RANK_2_[LH39.0_HL-2.17]_삼성전자/contents_png.png",
        "ChartBokeh_html": "html_stock/1034_코스피100/1d/RANK_2_[LH39.0_HL-2.17]_삼성전자/ChartBokeh.html",
        "clos_csv": "html_stock/1034_코스피100/1d/RANK_2_[LH39.0_HL-2.17]_삼성전자/clos.csv",
        "itemj_son": "html_stock/1034_코스피100/1d/RANK_2_[LH39.0_HL-2.17]_삼성전자/item.json"
    }
]