[
    {
        "report_md": "html_stock/2203_코스닥150/1d/RANK_7_[LH5.0_HL-21.86]_에스에프에이/report.md",
        "report_csv": "html_stock/2203_코스닥150/1d/RANK_7_[LH5.0_HL-21.86]_에스에프에이/report.csv",
        "bodycontents_html": "html_stock/2203_코스닥150/1d/RANK_7_[LH5.0_HL-21.86]_에스에프에이/bodycontents.html",
        "view_md": "html_stock/2203_코스닥150/1d/RANK_7_[LH5.0_HL-21.86]_에스에프에이/view.md",
        "ptlotlychart_md": "html_stock/2203_코스닥150/1d/RANK_7_[LH5.0_HL-21.86]_에스에프에이/ptlotlychart.md",
        "ptlotlychart_png": "html_stock/2203_코스닥150/1d/RANK_7_[LH5.0_HL-21.86]_에스에프에이/ptlotlychart.png",
        "thumbnail_png": "html_stock/2203_코스닥150/1d/RANK_7_[LH5.0_HL-21.86]_에스에프에이/thumbnail_png.png",
        "contents_png": "html_stock/2203_코스닥150/1d/RANK_7_[LH5.0_HL-21.86]_에스에프에이/contents_png.png",
        "ChartBokeh_html": "html_stock/2203_코스닥150/1d/RANK_7_[LH5.0_HL-21.86]_에스에프에이/ChartBokeh.html",
        "clos_csv": "html_stock/2203_코스닥150/1d/RANK_7_[LH5.0_HL-21.86]_에스에프에이/clos.csv",
        "itemj_son": "html_stock/2203_코스닥150/1d/RANK_7_[LH5.0_HL-21.86]_에스에프에이/item.json"
    }
]