[
    {
        "report_md": "html_stock/2203_코스닥150/1d/RANK_7_[LH7.77_HL-42.62]_스튜디오드래곤/report.md",
        "report_csv": "html_stock/2203_코스닥150/1d/RANK_7_[LH7.77_HL-42.62]_스튜디오드래곤/report.csv",
        "bodycontents_html": "html_stock/2203_코스닥150/1d/RANK_7_[LH7.77_HL-42.62]_스튜디오드래곤/bodycontents.html",
        "view_md": "html_stock/2203_코스닥150/1d/RANK_7_[LH7.77_HL-42.62]_스튜디오드래곤/view.md",
        "ptlotlychart_md": "html_stock/2203_코스닥150/1d/RANK_7_[LH7.77_HL-42.62]_스튜디오드래곤/ptlotlychart.md",
        "ptlotlychart_png": "html_stock/2203_코스닥150/1d/RANK_7_[LH7.77_HL-42.62]_스튜디오드래곤/ptlotlychart.png",
        "thumbnail_png": "html_stock/2203_코스닥150/1d/RANK_7_[LH7.77_HL-42.62]_스튜디오드래곤/thumbnail_png.png",
        "contents_png": "html_stock/2203_코스닥150/1d/RANK_7_[LH7.77_HL-42.62]_스튜디오드래곤/contents_png.png",
        "ChartBokeh_html": "html_stock/2203_코스닥150/1d/RANK_7_[LH7.77_HL-42.62]_스튜디오드래곤/ChartBokeh.html",
        "clos_csv": "html_stock/2203_코스닥150/1d/RANK_7_[LH7.77_HL-42.62]_스튜디오드래곤/clos.csv",
        "itemj_son": "html_stock/2203_코스닥150/1d/RANK_7_[LH7.77_HL-42.62]_스튜디오드래곤/item.json"
    }
]